README.txt
setup.cfg
setup.py
docs/HISTORY.txt
silva/__init__.py
silva.pas.radius.egg-info/PKG-INFO
silva.pas.radius.egg-info/SOURCES.txt
silva.pas.radius.egg-info/dependency_links.txt
silva.pas.radius.egg-info/namespace_packages.txt
silva.pas.radius.egg-info/not-zip-safe
silva.pas.radius.egg-info/requires.txt
silva.pas.radius.egg-info/top_level.txt
silva/pas/__init__.py
silva/pas/radius/__init__.py
silva/pas/radius/configure.zcml
silva/pas/radius/install.py
silva/pas/radius/interfaces.py
silva/pas/radius/radius.py
silva/pas/radius/plugins/__init__.py
silva/pas/radius/plugins/radius.py
silva/pas/radius/www/radius.png
silva/pas/radius/www/radiusAddForm.zpt
silva/pas/radius/www/radiusEditForm.zpt