Metadata-Version: 1.0
Name: silva.pas.radius
Version: 1.0
Summary: Radius support Silva
Home-page: https://svn.infrae.com/silva.pas.radius/trunk
Author: Sylvain Viollon
Author-email: info@infrae.com
License: ZPL and BSD
Keywords: pas silva radius authentication
Platform: UNKNOWN
Classifier: Framework :: Zope2
Classifier: Programming Language :: Python
Classifier: Topic :: Software Development :: Libraries :: Python Modules
Classifier: License :: OSI Approved :: BSD License
